odoo/addons/fs_base_multi_image/README.rst
odoo/addons/fs_base_multi_image/__init__.py
odoo/addons/fs_base_multi_image/__manifest__.py
odoo/addons/fs_base_multi_image/i18n/es.po
odoo/addons/fs_base_multi_image/i18n/fr.po
odoo/addons/fs_base_multi_image/i18n/fs_base_multi_image.pot
odoo/addons/fs_base_multi_image/i18n/it.po
odoo/addons/fs_base_multi_image/models/__init__.py
odoo/addons/fs_base_multi_image/models/fs_image.py
odoo/addons/fs_base_multi_image/models/fs_image_relation_mixin.py
odoo/addons/fs_base_multi_image/readme/CONTRIBUTORS.md
odoo/addons/fs_base_multi_image/readme/DESCRIPTION.md
odoo/addons/fs_base_multi_image/readme/ROADMAP.md
odoo/addons/fs_base_multi_image/readme/USAGE.md
odoo/addons/fs_base_multi_image/security/fs_image.xml
odoo/addons/fs_base_multi_image/security/res_groups.xml
odoo/addons/fs_base_multi_image/static/description/icon.png
odoo/addons/fs_base_multi_image/static/description/index.html
odoo/addons/fs_base_multi_image/static/src/fields/fs_image_relation_dnd_upload/fs_image_relation_dnd_upload.esm.js
odoo/addons/fs_base_multi_image/static/src/fields/fs_image_relation_dnd_upload/fs_image_relation_dnd_upload.scss
odoo/addons/fs_base_multi_image/static/src/fields/fs_image_relation_dnd_upload/fs_image_relation_dnd_upload.xml
odoo/addons/fs_base_multi_image/views/fs_image.xml
odoo/addons/fs_base_multi_image/views/fs_image_relation_mixin.xml
odoo_addon_fs_base_multi_image-17.0.1.0.1.2.dist-info/METADATA
odoo_addon_fs_base_multi_image-17.0.1.0.1.2.dist-info/WHEEL
odoo_addon_fs_base_multi_image-17.0.1.0.1.2.dist-info/top_level.txt
odoo_addon_fs_base_multi_image-17.0.1.0.1.2.dist-info/RECORD
